cluster_viz/__init__.py
cluster_viz/_version.py
cluster_viz-1.2.5.data/data/share/jupyter/labextensions/cluster_viz/package.json
cluster_viz-1.2.5.data/data/share/jupyter/labextensions/cluster_viz/static/107.9e280dce331abb0ee3be.js
cluster_viz-1.2.5.data/data/share/jupyter/labextensions/cluster_viz/static/383.59b4828189adcf58ebb0.js
cluster_viz-1.2.5.data/data/share/jupyter/labextensions/cluster_viz/static/540.3b012ff7e1b036419589.js
cluster_viz-1.2.5.data/data/share/jupyter/labextensions/cluster_viz/static/540.3b012ff7e1b036419589.js.LICENSE.txt
cluster_viz-1.2.5.data/data/share/jupyter/labextensions/cluster_viz/static/693.84cc83964e33eaea731e.js
cluster_viz-1.2.5.data/data/share/jupyter/labextensions/cluster_viz/static/728.e80b1622a759498c7593.js
cluster_viz-1.2.5.data/data/share/jupyter/labextensions/cluster_viz/static/747.80985a27f109d8440625.js
cluster_viz-1.2.5.data/data/share/jupyter/labextensions/cluster_viz/static/879.fc65a247ea6990899d69.js
cluster_viz-1.2.5.data/data/share/jupyter/labextensions/cluster_viz/static/remoteEntry.c5ceaaf2feade4dff5ce.js
cluster_viz-1.2.5.data/data/share/jupyter/labextensions/cluster_viz/static/style.js
cluster_viz-1.2.5.data/data/share/jupyter/labextensions/cluster_viz/static/third-party-licenses.json
cluster_viz-1.2.5.data/data/share/jupyter/labextensions/cluster_viz/install.json
cluster_viz-1.2.5.dist-info/METADATA
cluster_viz-1.2.5.dist-info/WHEEL
cluster_viz-1.2.5.dist-info/licenses/LICENSE
cluster_viz-1.2.5.dist-info/RECORD
