Metadata-Version: 2.3
Name: cluster_viz
Version: 1.2.5
Dynamic: Keywords
Summary: Show a random NASA Astronomy Picture of the Day in a JupyterLab panel
Project-URL: Homepage, https://github.com/ETH-PEACH-Lab/datascience-visualisation
Project-URL: Bug Tracker, https://github.com/ETH-PEACH-Lab/datascience-visualisation/issues
Project-URL: Repository, https://github.com/ETH-PEACH-Lab/datascience-visualisation
Author: My Name
License: BSD 3-Clause License
License-File: LICENSE
Classifier: Framework :: Jupyter
Classifier: Framework :: Jupyter :: JupyterLab
Classifier: Framework :: Jupyter :: JupyterLab :: 4
Classifier: Framework :: Jupyter :: JupyterLab :: Extensions
Classifier: Framework :: Jupyter :: JupyterLab :: Extensions :: Prebuilt
Classifier: License :: OSI Approved :: BSD License
Classifier: Programming Language :: Python
Classifier: Programming Language :: Python :: 3
Classifier: Programming Language :: Python :: 3.8
Classifier: Programming Language :: Python :: 3.9
Classifier: Programming Language :: Python :: 3.10
Classifier: Programming Language :: Python :: 3.11
Classifier: Programming Language :: Python :: 3.12
Requires-Python: >=3.8
